function/__init__.py
function/func.py
test/__init__.py
test/test_add.py
test/test_hello.py
test/test_randomarray.py
jihun_test-1.3.1.dist-info/METADATA
jihun_test-1.3.1.dist-info/WHEEL
jihun_test-1.3.1.dist-info/top_level.txt
jihun_test-1.3.1.dist-info/RECORD
