Metadata-Version: 2.1
Name: jihun-test
Version: 1.3.1
Summary: Simple Packaging by Python, jihun
Home-page: UNKNOWN
Author: jihun
Author-email: pj522h@gmail.com
License: UNKNOWN
Keywords: test,package
Platform: UNKNOWN
Classifier: Programming Language :: Python :: 3
Classifier: License :: OSI Approved :: MIT License
Classifier: Operating System :: OS Independent
Requires-Python: >=3.6
Requires-Dist: numpy (==1.20.0)
